{
  "type": "output",
  "connectors": [
    {
      "type": "connector--output",
      "accept": "connector--input"
    }
  ],
  "name": "Argument",
  "content": [
    [
      {
        "alias": "text",
        "value": "variable"
      },
      {
        "id": "TYPE",
        "alias": "dropdown",
        "options": [
          {
            "label": "float",
            "value": "float"
          },
          {
            "label": "String",
            "value": "String"
          },
          {
            "label": "bool",
            "value": "bool"
          }
        ]
      },
      {
        "id": "VARNAME",
        "alias": "varInput",
        "value": "x"
      }
    ]
  ],
  "code": "{TYPE} {VARNAME}"
}