{
  "type": "output",
  "name": "arguments",
  "connectors": [
    {
      "type": "connector--output",
      "accept": "connector--input"
    },
    {
      "type": "connector--input",
      "accept": "connector--output",
      "acceptType": "all",
      "name": "6a4072d6-1779-4f15-9986-0037d7367b14"
    },
    {
      "type": "connector--input",
      "accept": "connector--output",
      "acceptType": "all",
      "name": "0b48d186-fb9f-4c29-a431-79784b1f6659"
    }
  ],
  "bloqClass": "bloq-arguments",
  "content": [
    [
      {
        "bloqInputId": "ARG1",
        "alias": "bloqInput",
        "acceptType": "all",
        "name": "6a4072d6-1779-4f15-9986-0037d7367b14"
      },
      {
        "alias": "text",
        "value": ","
      },
      {
        "bloqInputId": "ARG2",
        "alias": "bloqInput",
        "acceptType": "all",
        "name": "0b48d186-fb9f-4c29-a431-79784b1f6659"
      }
    ]
  ],
  "createDynamicContent": "softwareVars",
  "code": "{ARG1},{ARG2}",
  "returnType": {
    "type": "simple",
    "value": "var"
  }
}