{
  "type": "output",
  "name": "substringAdvanced",
  "connectors": [
    {
      "type": "connector--output",
      "accept": "connector--input"
    },
    {
      "type": "connector--input",
      "accept": "connector--output",
      "acceptType": [
        "all"
      ],
      "suggestedBloqs": [
        "selectVariable"
      ],
      "name": "e58c0bed-cbec-4789-b81d-6b94233502cb"
    },
    {
      "type": "connector--input",
      "accept": "connector--output",
      "acceptType": [
        "all"
      ],
      "suggestedBloqs": [
        "number",
        "selectVariable"
      ],
      "name": "6d796df1-ea92-44f2-8273-e39d90cc0286"
    },
    {
      "type": "connector--input",
      "accept": "connector--output",
      "acceptType": [
        "all"
      ],
      "suggestedBloqs": [
        "number",
        "selectVariable"
      ],
      "name": "bb9e9e84-ec07-4efe-aaa8-62b00903a10f"
    }
  ],
  "bloqClass": "bloq-string",
  "content": [
    [
      {
        "alias": "text",
        "value": "Extraer texto de"
      },
      {
        "bloqInputId": "STRING",
        "alias": "bloqInput",
        "acceptType": [
          "all"
        ],
        "suggestedBloqs": [
          "selectVariable"
        ],
        "name": "e58c0bed-cbec-4789-b81d-6b94233502cb"
      },
      {
        "alias": "text",
        "value": "empezando en la posición"
      },
      {
        "bloqInputId": "FROM",
        "alias": "bloqInput",
        "acceptType": [
          "all"
        ],
        "suggestedBloqs": [
          "number",
          "selectVariable"
        ],
        "name": "6d796df1-ea92-44f2-8273-e39d90cc0286"
      },
      {
        "alias": "text",
        "value": "y acabando en la posición"
      },
      {
        "bloqInputId": "TO",
        "alias": "bloqInput",
        "acceptType": [
          "all"
        ],
        "suggestedBloqs": [
          "number",
          "selectVariable"
        ],
        "name": "bb9e9e84-ec07-4efe-aaa8-62b00903a10f"
      }
    ]
  ],
  "returnType": {
    "type": "simple",
    "value": "String"
  },
  "arduino": {
    "code": "{STRING}.substring({FROM}, {TO})"
  },
  "python": {
    "codeLines": [
      {
        "code": "Bloque \"substringAdvanced\" no preparado para generar código python"
      }
    ]
  }
}