{
  "type": "statement-input",
  "name": "whileAdvanced",
  "connectors": [
    {
      "type": "connector--top",
      "accept": "connector--bottom"
    },
    {
      "type": "connector--bottom",
      "accept": "connector--top"
    },
    {
      "type": "connector--root",
      "accept": "connector--top"
    },
    {
      "type": "connector--input",
      "accept": "connector--output",
      "acceptType": [
        "all"
      ],
      "name": "8cb2978d-6a9f-44f4-b562-da1d73a22142"
    }
  ],
  "bloqClass": "bloq-while",
  "content": [
    [
      {
        "alias": "text",
        "value": "bloq-while-while"
      },
      {
        "bloqInputId": "CONDITION",
        "alias": "bloqInput",
        "acceptType": [
          "all"
        ],
        "name": "8cb2978d-6a9f-44f4-b562-da1d73a22142"
      },
      {
        "alias": "text",
        "value": "bloq-while-exec"
      }
    ]
  ],
  "code": "while ({CONDITION}){{STATEMENTS}}"
}