{
  "type": "statement",
  "name": "analogWrite",
  "connectors": [
    {
      "type": "connector--top",
      "accept": "connector--bottom"
    },
    {
      "type": "connector--bottom",
      "accept": "connector--top"
    },
    {
      "type": "connector--input",
      "accept": "connector--output",
      "acceptType": [
        "all"
      ],
      "name": "f80b4c9b-20a3-43ee-a654-f4f6008f9f79"
    },
    {
      "type": "connector--input",
      "accept": "connector--output",
      "acceptType": [
        "all"
      ],
      "name": "ba59787c-0804-46dc-9b3e-45a133a57dc6"
    }
  ],
  "bloqClass": "bloq-pin-writte-advanced",
  "content": [
    [
      {
        "alias": "text",
        "value": "bloq-pin-analog-write-V1"
      },
      {
        "bloqInputId": "PIN",
        "alias": "bloqInput",
        "acceptType": [
          "all"
        ],
        "name": "f80b4c9b-20a3-43ee-a654-f4f6008f9f79"
      },
      {
        "alias": "text",
        "value": "bloq-pin-analog-write-data-V1"
      },
      {
        "bloqInputId": "DATA",
        "alias": "bloqInput",
        "acceptType": [
          "all"
        ],
        "name": "ba59787c-0804-46dc-9b3e-45a133a57dc6"
      }
    ]
  ],
  "code": "'{PIN}'.indexOf('A') !== -1 ? 'analogWrite({PIN},{DATA});'.replace(/\"/g, '') : 'analogWrite({PIN},{DATA});'"
}