{
  "type": "statement",
  "name": "continuousServoStartAdvanced-v1",
  "connectors": [
    {
      "type": "connector--top",
      "accept": "connector--bottom"
    },
    {
      "type": "connector--bottom",
      "accept": "connector--top"
    },
    {
      "type": "connector--input",
      "accept": "connector--output",
      "acceptType": "all",
      "name": "fe584b05-1578-4882-9005-31a0b924879c"
    },
    {
      "type": "connector--input",
      "accept": "connector--output",
      "acceptType": "all",
      "name": "35be4c68-d446-44be-b1ce-c5bbb184c794"
    }
  ],
  "bloqClass": "bloq-continuous-servo-start-advanced",
  "content": [
    [
      {
        "alias": "text",
        "value": "bloq-continuous-servo-start-advanced-turn"
      },
      {
        "bloqInputId": "SERVO",
        "alias": "bloqInput",
        "acceptType": "all",
        "name": "fe584b05-1578-4882-9005-31a0b924879c"
      },
      {
        "alias": "text",
        "value": "bloq-continuous-servo-start-advanced-direction"
      },
      {
        "bloqInputId": "DIRECTION",
        "alias": "bloqInput",
        "acceptType": "all",
        "name": "35be4c68-d446-44be-b1ce-c5bbb184c794"
      }
    ]
  ],
  "code": "{SERVO}.write({DIRECTION});"
}