{
  "type": "statement",
  "name": "continuousServoStartAdvanced-v1",
  "connectors": [
    {
      "type": "connector--top",
      "accept": "connector--bottom"
    },
    {
      "type": "connector--bottom",
      "accept": "connector--top"
    },
    {
      "type": "connector--input",
      "accept": "connector--output",
      "acceptType": [
        "all"
      ],
      "suggestedBloqs": [
        "hwVariable",
        "selectVariable"
      ],
      "name": "4aae905b-7664-488e-be2b-224b3901eb3d"
    },
    {
      "type": "connector--input",
      "accept": "connector--output",
      "acceptType": [
        "all"
      ],
      "suggestedBloqs": [
        "number",
        "selectVariable"
      ],
      "name": "bdc3c751-d29b-4e01-89ac-230287d8a512"
    }
  ],
  "bloqClass": "bloq-continuous-servo-start-advanced",
  "content": [
    [
      {
        "alias": "text",
        "value": "bloq-continuous-servo-start-advanced-turn"
      },
      {
        "bloqInputId": "SERVO",
        "alias": "bloqInput",
        "acceptType": [
          "all"
        ],
        "suggestedBloqs": [
          "hwVariable",
          "selectVariable"
        ],
        "name": "4aae905b-7664-488e-be2b-224b3901eb3d"
      },
      {
        "alias": "text",
        "value": "bloq-continuous-servo-start-advanced-direction"
      },
      {
        "bloqInputId": "DIRECTION",
        "alias": "bloqInput",
        "acceptType": [
          "all"
        ],
        "suggestedBloqs": [
          "number",
          "selectVariable"
        ],
        "name": "bdc3c751-d29b-4e01-89ac-230287d8a512"
      }
    ]
  ],
  "code": "{SERVO}.write({DIRECTION});",
  "arduino": {
    "code": "{SERVO}.write({DIRECTION});"
  },
  "python": {
    "codeLines": [
      {
        "code": "Bloque \"continuousServoStartAdvanced-v1\" no preparado para generar código python"
      }
    ]
  }
}