{
  "type": "statement",
  "name": "lcdWriteAdvanced",
  "connectors": [
    {
      "type": "connector--top",
      "accept": "connector--bottom"
    },
    {
      "type": "connector--bottom",
      "accept": "connector--top"
    },
    {
      "type": "connector--input",
      "accept": "connector--output",
      "acceptType": [
        "all"
      ],
      "suggestedBloqs": [
        "string",
        "selectVariable"
      ],
      "name": "4615c556-96a6-4b7b-988f-62129d4bd8f0"
    },
    {
      "type": "connector--input",
      "accept": "connector--output",
      "acceptType": [
        "all"
      ],
      "suggestedBloqs": [
        "hwVariable",
        "selectVariable"
      ],
      "name": "f14180a3-2f72-4584-8fd4-259cdd8ec58e"
    }
  ],
  "bloqClass": "bloq-lcd-writte-advanced",
  "content": [
    [
      {
        "alias": "text",
        "value": "bloq-lcd-writte-advanced-write"
      },
      {
        "bloqInputId": "TEXT",
        "alias": "bloqInput",
        "acceptType": [
          "all"
        ],
        "suggestedBloqs": [
          "string",
          "selectVariable"
        ],
        "name": "4615c556-96a6-4b7b-988f-62129d4bd8f0"
      },
      {
        "alias": "text",
        "value": "bloq-lcd-writte-advanced-inLCD"
      },
      {
        "bloqInputId": "LCD",
        "alias": "bloqInput",
        "acceptType": [
          "all"
        ],
        "suggestedBloqs": [
          "hwVariable",
          "selectVariable"
        ],
        "name": "f14180a3-2f72-4584-8fd4-259cdd8ec58e"
      }
    ]
  ],
  "code": "{LCD}.print({TEXT});",
  "arduino": {
    "code": "{LCD}.print({TEXT});"
  },
  "python": {
    "codeLines": [
      {
        "code": "Bloque \"lcdWriteAdvanced\" no preparado para generar código python"
      }
    ]
  }
}