{
  "type": "output",
  "name": "random",
  "connectors": [
    {
      "type": "connector--output",
      "accept": "connector--input"
    },
    {
      "type": "connector--input",
      "accept": "connector--output",
      "acceptType": "float",
      "name": "a8c33241-5f35-47e1-a48d-6a5f19b27c34"
    },
    {
      "type": "connector--input",
      "accept": "connector--output",
      "acceptType": "float",
      "name": "7378b31c-1052-4b86-9280-2511e8d78cee"
    }
  ],
  "bloqClass": "bloq-random",
  "content": [
    [
      {
        "alias": "text",
        "value": "bloq-random-random"
      },
      {
        "bloqInputId": "ARG1",
        "alias": "bloqInput",
        "acceptType": "float",
        "name": "a8c33241-5f35-47e1-a48d-6a5f19b27c34"
      },
      {
        "alias": "text",
        "value": "bloq-random-and"
      },
      {
        "bloqInputId": "ARG2",
        "alias": "bloqInput",
        "acceptType": "float",
        "name": "7378b31c-1052-4b86-9280-2511e8d78cee"
      }
    ]
  ],
  "code": "random({ARG1},{ARG2}+1)",
  "returnType": {
    "type": "simple",
    "value": "float"
  }
}