{
  "type": "output",
  "name": "logicOperations",
  "connectors": [
    {
      "type": "connector--output",
      "accept": "connector--input"
    },
    {
      "type": "connector--input",
      "accept": "connector--output",
      "acceptType": [
        "all"
      ],
      "suggestedBloqs": [
        "selectVariable",
        "equalityOperations",
        "logicOperations"
      ],
      "name": "ed7c74d9-cb7e-41ca-b9f7-bf140b57178c"
    },
    {
      "type": "connector--input",
      "accept": "connector--output",
      "acceptType": [
        "all"
      ],
      "suggestedBloqs": [
        "selectVariable",
        "equalityOperations",
        "logicOperations"
      ],
      "name": "2547c7d1-b333-409e-85a5-3354b0797c4e"
    }
  ],
  "bloqClass": "bloq-logic-operations",
  "content": [
    [
      {
        "bloqInputId": "ARG1",
        "alias": "bloqInput",
        "acceptType": [
          "all"
        ],
        "suggestedBloqs": [
          "selectVariable",
          "equalityOperations",
          "logicOperations"
        ],
        "name": "ed7c74d9-cb7e-41ca-b9f7-bf140b57178c"
      },
      {
        "id": "OPERATOR",
        "alias": "staticDropdown",
        "options": [
          {
            "label": "bloq-logic-operations-and",
            "value": "&&"
          },
          {
            "label": "bloq-logic-operations-or",
            "value": "||"
          }
        ]
      },
      {
        "bloqInputId": "ARG2",
        "alias": "bloqInput",
        "acceptType": [
          "all"
        ],
        "suggestedBloqs": [
          "selectVariable",
          "equalityOperations",
          "logicOperations"
        ],
        "name": "2547c7d1-b333-409e-85a5-3354b0797c4e"
      }
    ]
  ],
  "code": "({ARG1} {OPERATOR} {ARG2})",
  "returnType": {
    "type": "simple",
    "value": "bool"
  }
}