{
  "type": "output",
  "name": "not",
  "connectors": [
    {
      "type": "connector--output",
      "accept": "connector--input"
    },
    {
      "type": "connector--input",
      "accept": "connector--output",
      "acceptType": [
        "all"
      ],
      "name": "eddb5504-367b-4a8b-aa15-1f79103663d0"
    }
  ],
  "bloqClass": "bloq-not",
  "content": [
    [
      {
        "alias": "text",
        "value": "bloq-not-not"
      },
      {
        "bloqInputId": "CONDITION",
        "alias": "bloqInput",
        "acceptType": [
          "all"
        ],
        "name": "eddb5504-367b-4a8b-aa15-1f79103663d0"
      }
    ]
  ],
  "code": "!{CONDITION}",
  "returnType": {
    "type": "simple",
    "value": "bool"
  }
}