{
  "type": "output",
  "name": "not",
  "connectors": [
    {
      "type": "connector--output",
      "accept": "connector--input"
    },
    {
      "type": "connector--input",
      "accept": "connector--output",
      "acceptType": [
        "all"
      ],
      "suggestedBloqs": [
        "selectVariable"
      ],
      "name": "33912c24-5f3f-46ae-b788-cca1b97a552d"
    }
  ],
  "bloqClass": "bloq-not",
  "content": [
    [
      {
        "alias": "text",
        "value": "bloq-not-not"
      },
      {
        "bloqInputId": "CONDITION",
        "alias": "bloqInput",
        "acceptType": [
          "all"
        ],
        "suggestedBloqs": [
          "selectVariable"
        ],
        "name": "33912c24-5f3f-46ae-b788-cca1b97a552d"
      }
    ]
  ],
  "code": "!{CONDITION}",
  "returnType": {
    "type": "simple",
    "value": "bool"
  },
  "arduino": {
    "code": "!{CONDITION}"
  },
  "python": {
    "codeLines": [
      {
        "code": "Bloque \"not\" no preparado para generar código python"
      }
    ]
  }
}