{
  "type": "statement",
  "name": "botbloqManipulatorMoveOnSpaceAdvanced",
  "connectors": [
    {
      "type": "connector--top",
      "accept": "connector--bottom"
    },
    {
      "type": "connector--bottom",
      "accept": "connector--top"
    },
    {
      "type": "connector--input",
      "accept": "connector--output",
      "acceptType": [
        "all"
      ],
      "suggestedBloqs": [
        "number",
        "selectVariable"
      ],
      "name": "5c432865-eef7-481c-baf8-682129183576"
    },
    {
      "type": "connector--input",
      "accept": "connector--output",
      "acceptType": [
        "all"
      ],
      "suggestedBloqs": [
        "number",
        "selectVariable"
      ],
      "name": "071514c7-ebc9-458a-b810-1c18be5fbadc"
    },
    {
      "type": "connector--input",
      "accept": "connector--output",
      "acceptType": [
        "all"
      ],
      "suggestedBloqs": [
        "number",
        "selectVariable"
      ],
      "name": "01e5ce78-f85c-4b63-9dae-ad9bf8962f34"
    }
  ],
  "bloqClass": "bloq-botbloq-manipulator-moveonspace",
  "content": [
    [
      {
        "alias": "text",
        "value": "Desplazarse a"
      },
      {
        "alias": "text",
        "value": "x:"
      },
      {
        "bloqInputId": "X",
        "alias": "bloqInput",
        "acceptType": [
          "all"
        ],
        "suggestedBloqs": [
          "number",
          "selectVariable"
        ],
        "name": "5c432865-eef7-481c-baf8-682129183576"
      },
      {
        "alias": "text",
        "value": "y:"
      },
      {
        "bloqInputId": "Y",
        "alias": "bloqInput",
        "acceptType": [
          "all"
        ],
        "suggestedBloqs": [
          "number",
          "selectVariable"
        ],
        "name": "071514c7-ebc9-458a-b810-1c18be5fbadc"
      },
      {
        "alias": "text",
        "value": "z:"
      },
      {
        "bloqInputId": "Z",
        "alias": "bloqInput",
        "acceptType": [
          "all"
        ],
        "suggestedBloqs": [
          "number",
          "selectVariable"
        ],
        "name": "01e5ce78-f85c-4b63-9dae-ad9bf8962f34"
      }
    ]
  ],
  "code": "",
  "python": {
    "libraries": [
      "BotbloqManipulator"
    ],
    "needInstanceOf": [
      {
        "name": "manipulator",
        "type": "BotbloqManipulator"
      }
    ],
    "codeLines": [
      {
        "code": "manipulator.move({X}, {Y}, {Z})"
      }
    ]
  }
}