{
  "type": "output",
  "name": "botbloqManipulatorCanMoveAdvanced",
  "connectors": [
    {
      "type": "connector--output",
      "accept": "connector--input"
    },
    {
      "type": "connector--input",
      "accept": "connector--output",
      "acceptType": [
        "all"
      ],
      "suggestedBloqs": [
        "number",
        "selectVariable"
      ],
      "name": "39ce276d-08bc-49c5-8fa1-75a317344678"
    },
    {
      "type": "connector--input",
      "accept": "connector--output",
      "acceptType": [
        "all"
      ],
      "suggestedBloqs": [
        "number",
        "selectVariable"
      ],
      "name": "1215fe0e-fcb9-4ef7-b172-36f2573da746"
    },
    {
      "type": "connector--input",
      "accept": "connector--output",
      "acceptType": [
        "all"
      ],
      "suggestedBloqs": [
        "number",
        "selectVariable"
      ],
      "name": "8edbca2b-55ae-492f-832c-e42d44f21044"
    }
  ],
  "bloqClass": "bloq-botbloq-manipulator-canmove",
  "content": [
    [
      {
        "alias": "text",
        "value": "can-move-to"
      },
      {
        "alias": "text",
        "value": "x:"
      },
      {
        "bloqInputId": "X",
        "alias": "bloqInput",
        "acceptType": [
          "all"
        ],
        "suggestedBloqs": [
          "number",
          "selectVariable"
        ],
        "name": "39ce276d-08bc-49c5-8fa1-75a317344678"
      },
      {
        "alias": "text",
        "value": "y:"
      },
      {
        "bloqInputId": "Y",
        "alias": "bloqInput",
        "acceptType": [
          "all"
        ],
        "suggestedBloqs": [
          "number",
          "selectVariable"
        ],
        "name": "1215fe0e-fcb9-4ef7-b172-36f2573da746"
      },
      {
        "alias": "text",
        "value": "z:"
      },
      {
        "bloqInputId": "Z",
        "alias": "bloqInput",
        "acceptType": [
          "all"
        ],
        "suggestedBloqs": [
          "number",
          "selectVariable"
        ],
        "name": "8edbca2b-55ae-492f-832c-e42d44f21044"
      },
      {
        "alias": "text",
        "value": "?"
      }
    ]
  ],
  "code": "",
  "returnType": {
    "type": "simple",
    "value": "bool"
  },
  "python": {
    "libraries": [
      "BotbloqManipulator"
    ],
    "needInstanceOf": [
      {
        "name": "manipulator",
        "type": "BotbloqManipulator"
      }
    ],
    "codeLines": [
      {
        "code": "vehicle.canMove({X}, {Y}, {Z})"
      }
    ]
  }
}