{
  "type": "statement",
  "name": "botbloqManipulatorMoveOnSpaceAdvanced",
  "connectors": [
    {
      "type": "connector--top",
      "accept": "connector--bottom"
    },
    {
      "type": "connector--bottom",
      "accept": "connector--top"
    },
    {
      "type": "connector--input",
      "accept": "connector--output",
      "acceptType": [
        "all"
      ],
      "suggestedBloqs": [
        "number",
        "selectVariable"
      ],
      "name": "9ddefca8-6130-4192-98ad-f91c3aa43903"
    },
    {
      "type": "connector--input",
      "accept": "connector--output",
      "acceptType": [
        "all"
      ],
      "suggestedBloqs": [
        "number",
        "selectVariable"
      ],
      "name": "64b66fa2-2a3e-4aa0-a224-d011dbf70e95"
    },
    {
      "type": "connector--input",
      "accept": "connector--output",
      "acceptType": [
        "all"
      ],
      "suggestedBloqs": [
        "number",
        "selectVariable"
      ],
      "name": "96ee81b2-8a25-45f5-b76a-f0f482010d00"
    }
  ],
  "bloqClass": "bloq-botbloq-manipulator-moveonspace",
  "content": [
    [
      {
        "alias": "text",
        "value": "Desplazarse a"
      },
      {
        "alias": "text",
        "value": "x:"
      },
      {
        "bloqInputId": "X",
        "alias": "bloqInput",
        "acceptType": [
          "all"
        ],
        "suggestedBloqs": [
          "number",
          "selectVariable"
        ],
        "name": "9ddefca8-6130-4192-98ad-f91c3aa43903"
      },
      {
        "alias": "text",
        "value": "y:"
      },
      {
        "bloqInputId": "Y",
        "alias": "bloqInput",
        "acceptType": [
          "all"
        ],
        "suggestedBloqs": [
          "number",
          "selectVariable"
        ],
        "name": "64b66fa2-2a3e-4aa0-a224-d011dbf70e95"
      },
      {
        "alias": "text",
        "value": "z:"
      },
      {
        "bloqInputId": "Z",
        "alias": "bloqInput",
        "acceptType": [
          "all"
        ],
        "suggestedBloqs": [
          "number",
          "selectVariable"
        ],
        "name": "96ee81b2-8a25-45f5-b76a-f0f482010d00"
      }
    ]
  ],
  "code": "",
  "python": {
    "libraries": [
      "BotbloqManipulator"
    ],
    "needInstanceOf": [
      {
        "name": "manipulator",
        "type": "BotbloqManipulator"
      }
    ],
    "codeLines": [
      {
        "code": "manipulator.move({X}, {Y}, {Z})"
      }
    ]
  }
}