{
  "type": "output",
  "name": "arguments",
  "connectors": [
    {
      "type": "connector--output",
      "accept": "connector--input"
    },
    {
      "type": "connector--input",
      "accept": "connector--output",
      "acceptType": [
        "all"
      ],
      "name": "6eb40a82-ec3e-4ffd-b8dd-bce6b6b6c2e2"
    },
    {
      "type": "connector--input",
      "accept": "connector--output",
      "acceptType": [
        "all"
      ],
      "name": "977d73e4-a7b9-40c6-8b1c-d4bfb8d940c5"
    }
  ],
  "bloqClass": "bloq-arguments",
  "content": [
    [
      {
        "bloqInputId": "ARG1",
        "alias": "bloqInput",
        "acceptType": [
          "all"
        ],
        "name": "6eb40a82-ec3e-4ffd-b8dd-bce6b6b6c2e2"
      },
      {
        "alias": "text",
        "value": ","
      },
      {
        "bloqInputId": "ARG2",
        "alias": "bloqInput",
        "acceptType": [
          "all"
        ],
        "name": "977d73e4-a7b9-40c6-8b1c-d4bfb8d940c5"
      }
    ]
  ],
  "createDynamicContent": "softwareVars",
  "code": "{ARG1},{ARG2}",
  "returnType": {
    "type": "simple",
    "value": "var"
  }
}