{
  "type": "statement-input",
  "name": "returnFunctionWithArguments",
  "connectors": [
    {
      "type": "connector--top",
      "accept": "connector--bottom"
    },
    {
      "type": "connector--bottom",
      "accept": "connector--top"
    },
    {
      "type": "connector--root",
      "accept": "connector--top"
    },
    {
      "type": "connector--input",
      "accept": "connector--output",
      "acceptType": [
        "all"
      ],
      "name": "289ea61c-f11c-4244-aa7f-ded8e2c8b708"
    },
    {
      "type": "connector--input",
      "accept": "connector--output",
      "acceptType": [
        "all"
      ],
      "name": "a4d30735-3f3a-407a-a91d-d28a36fec6bc"
    }
  ],
  "bloqClass": "bloq-return-function-with-arguments",
  "content": [
    [
      {
        "alias": "text",
        "value": "bloq-return-function-with-arguments-declare"
      },
      {
        "id": "FUNCNAME",
        "alias": "varInput",
        "placeholder": "bloq-functions-default"
      },
      {
        "alias": "text",
        "value": "bloq-return-function-with-arguments-count"
      },
      {
        "bloqInputId": "ARGS",
        "alias": "bloqInput",
        "acceptType": [
          "all"
        ],
        "name": "289ea61c-f11c-4244-aa7f-ded8e2c8b708"
      },
      {
        "position": "DOWN",
        "alias": "text",
        "value": "bloq-return-function-with-arguments-return"
      },
      {
        "position": "DOWN",
        "bloqInputId": "RETURN",
        "alias": "bloqInput",
        "acceptType": [
          "all"
        ],
        "name": "a4d30735-3f3a-407a-a91d-d28a36fec6bc"
      }
    ]
  ],
  "createDynamicContent": "returnFunctions",
  "returnType": {
    "type": "fromInput",
    "bloqInputId": "RETURN"
  },
  "arguments": {
    "type": "fromInput",
    "bloqInputId": "ARGS"
  },
  "code": "{RETURN.connectionType} {FUNCNAME} ({ARGS}) {{STATEMENTS}return {RETURN};}"
}