{
  "type": "statement-input",
  "name": "returnFunctionWithArguments",
  "connectors": [
    {
      "type": "connector--top",
      "accept": "connector--bottom"
    },
    {
      "type": "connector--bottom",
      "accept": "connector--top"
    },
    {
      "type": "connector--root",
      "accept": "connector--top"
    },
    {
      "type": "connector--input",
      "accept": "connector--output",
      "acceptType": [
        "all"
      ],
      "suggestedBloqs": [
        "argument",
        "arguments",
        "number",
        "string",
        "selectVariable"
      ],
      "name": "e2d905d9-33c2-4fd5-85a8-6ddbfdeb59e5"
    },
    {
      "type": "connector--input",
      "accept": "connector--output",
      "acceptType": [
        "all"
      ],
      "suggestedBloqs": [
        "selectVariable",
        "logicOperations",
        "equalityOperations"
      ],
      "name": "85c2952f-bbeb-4ff3-b0ce-7e80480743e5"
    }
  ],
  "bloqClass": "bloq-return-function-with-arguments",
  "content": [
    [
      {
        "alias": "text",
        "value": "bloq-return-function-with-arguments-declare"
      },
      {
        "id": "FUNCNAME",
        "alias": "varInput",
        "placeholder": "bloq-functions-default"
      },
      {
        "alias": "text",
        "value": "bloq-return-function-with-arguments-count"
      },
      {
        "bloqInputId": "ARGS",
        "alias": "bloqInput",
        "acceptType": [
          "all"
        ],
        "suggestedBloqs": [
          "argument",
          "arguments",
          "number",
          "string",
          "selectVariable"
        ],
        "name": "e2d905d9-33c2-4fd5-85a8-6ddbfdeb59e5"
      },
      {
        "position": "DOWN",
        "alias": "text",
        "value": "bloq-return-function-with-arguments-return"
      },
      {
        "position": "DOWN",
        "bloqInputId": "RETURN",
        "alias": "bloqInput",
        "acceptType": [
          "all"
        ],
        "suggestedBloqs": [
          "selectVariable",
          "logicOperations",
          "equalityOperations"
        ],
        "name": "85c2952f-bbeb-4ff3-b0ce-7e80480743e5"
      }
    ]
  ],
  "createDynamicContent": "returnFunctions",
  "returnType": {
    "type": "fromInput",
    "bloqInputId": "RETURN"
  },
  "code": "{RETURN.connectionType} {FUNCNAME} ({ARGS}) {{STATEMENTS}return {RETURN};}",
  "arduino": {
    "code": "@{RETURN.returnType} {FUNCNAME} ({ARGS}) {{STATEMENTS}return {RETURN};}"
  },
  "python": {
    "codeLines": [
      {
        "code": "Bloque \"returnFunctionWithArguments\" no preparado para generar código python"
      }
    ]
  }
}