{
  "type": "statement",
  "name": "setArrayVariable",
  "connectors": [
    {
      "type": "connector--top",
      "accept": "connector--bottom"
    },
    {
      "type": "connector--bottom",
      "accept": "connector--top"
    },
    {
      "type": "connector--input",
      "accept": "connector--output",
      "acceptType": {
        "type": "fromDynamicDropdown",
        "idDropdown": "NAME",
        "pointer": "true",
        "options": "softwareVars"
      },
      "name": "d7eaeb37-6b6c-4561-9fbc-a097283f46c6"
    }
  ],
  "bloqClass": "bloq-set-variableArray",
  "content": [
    [
      {
        "alias": "text",
        "value": "bloq-set-variableArray-variable"
      },
      {
        "id": "NAME",
        "alias": "dynamicDropdown",
        "options": "softwareVars"
      },
      {
        "alias": "text",
        "value": "["
      },
      {
        "id": "ITERATOR",
        "alias": "numberInput",
        "value": 0
      },
      {
        "alias": "text",
        "value": "]"
      },
      {
        "alias": "text",
        "value": "="
      },
      {
        "bloqInputId": "VALUE",
        "alias": "bloqInput",
        "acceptType": {
          "type": "fromDynamicDropdown",
          "idDropdown": "NAME",
          "pointer": "true",
          "options": "softwareVars"
        },
        "name": "d7eaeb37-6b6c-4561-9fbc-a097283f46c6"
      }
    ]
  ],
  "code": "{NAME}[{ITERATOR}] = {VALUE};"
}